rapid/__init__.py
rapid/core.py
rapid/decorators.py
rapid/schemas.py
rapid/views.py
django_rapid-0.2.0.dist-info/METADATA
django_rapid-0.2.0.dist-info/WHEEL
django_rapid-0.2.0.dist-info/RECORD
