Metadata-Version: 2.4
Name: django-rapid
Version: 0.2.0
Summary: Fast JSON validation and serialization for Django using msgspec
Author-email: Farhan Ali Raza <farhanalirazaazeemi@gmail.com>
Keywords: api,decoding,decorator,django,encoding,fast,json,json-api,model,msgspec,performance,queryset,rapid,request,response,rest,schema,serialization,struct,validation,view
Requires-Python: >=3.12
Requires-Dist: django>=5.2
Requires-Dist: msgspec>=0.18.0
Provides-Extra: dev
Requires-Dist: mypy>=1.0; extra == 'dev'
Requires-Dist: pytest-django>=4.5.0; extra == 'dev'
Requires-Dist: pytest>=7.0; extra == 'dev'
Requires-Dist: ruff>=0.1.0; extra == 'dev'
